{
  "server": {
    "host": "localhost",
    "allowLAN": true,
    "lanHost": "198.18.0.1",
    "enableCommandAPI": false
  },
  "projectDefaults": {
    "defaultTheme": null
  },
  "projectInfo": {
    "description": null
  },
  "cloudPublishing": {
    "vercel": {
      "token": "vcp_052lyMHCLR3MPQPjTZdqBd7jq3gEHDy6qdQZae9gYV1RfXcHBJ0T2YPC",
      "projectName": "axj-zhuangbei07",
      "teamId": ""
    },
    "cloudflarePages": {
      "apiToken": "",
      "accountId": "",
      "projectName": "",
      "productionBranch": "main"
    },
    "s3": {
      "accessKeyId": "",
      "secretAccessKey": "",
      "region": "",
      "bucket": "",
      "prefix": "",
      "baseUrl": "",
      "endpoint": ""
    },
    "githubPages": {
      "repository": "GongChangZhouKang/axjyun",
      "branch": "gh-pages",
      "sourceDirectory": "/"
    },
    "publishSettings": {
      "includeSource": false,
      "visibleTargets": [
        "axhub",
        "vercel"
      ]
    }
  }
}