{
  "bbox": {
    "height": 32,
    "left": 1812,
    "top": 207,
    "width": 64
  },
  "children": [
    "n241",
    "n245",
    "n251",
    "n257",
    "n263",
    "n269",
    "n274",
    "n280",
    "n286"
  ],
  "height": "48px",
  "nodeId": "n287",
  "originalClass": "ivu-table-row",
  "selector": "div.content-box.ivu-layout-content > div.new-big-box > div:nth-of-type(1) > div.new-search-box:nth-of-type(1) > div.right-btn:nth-of-type(5) > div.sms-btn:nth-of-type(2) > button.ivu-btn.ivu-btn-default",
  "styleId": "style_88",
  "tag": "tr",
  "width": "1755px"
}